<?xml version="1.0" encoding="utf-8" ?><dwsync><file name="copiae.mp3" server="wheelockslatin.com" local="3531618000" remote="3531618000" Dst="-1" /><file name="ad.mp3" server="wheelockslatin.com" local="3530581200" remote="3530581200" Dst="-1" /><file name="ago.mp3" server="wheelockslatin.com" local="3530581200" remote="3530581200" Dst="-1" /><file name="cicero.mp3" server="wheelockslatin.com" local="3530581200" remote="3530581200" Dst="-1" /><file name="copia.mp3" server="wheelockslatin.com" local="3530581200" remote="3530581200" Dst="-1" /><file name="demonstro.mp3" server="wheelockslatin.com" local="3530581200" remote="3530581200" Dst="-1" /><file name="disco.mp3" server="wheelockslatin.com" local="3530581200" remote="3530581200" Dst="-1" /><file name="doceo.mp3" server="wheelockslatin.com" local="3530581200" remote="3530581200" Dst="-1" /><file name="duco.mp3" server="wheelockslatin.com" local="3530581200" remote="3530581200" Dst="-1" /><file name="dum.mp3" server="wheelockslatin.com" local="3530581200" remote="3530581200" Dst="-1" /><file name="ex.mp3" server="wheelockslatin.com" local="3530581200" remote="3530581200" Dst="-1" /><file name="frater.mp3" server="wheelockslatin.com" local="3530667600" remote="3530667600" Dst="-1" /><file name="gero.mp3" server="wheelockslatin.com" local="3530667600" remote="3530667600" Dst="-1" /><file name="gratiasagere.mp3" server="wheelockslatin.com" local="3530667600" remote="3530667600" Dst="-1" /><file name="laus.mp3" server="wheelockslatin.com" local="3530667600" remote="3530667600" Dst="-1" /><file name="libertas.mp3" server="wheelockslatin.com" local="3530667600" remote="3530667600" Dst="-1" /><file name="numquam.mp3" server="wheelockslatin.com" local="3530667600" remote="3530667600" Dst="-1" /><file name="ratio.mp3" server="wheelockslatin.com" local="3530667600" remote="3530667600" Dst="-1" /><file name="scribo.mp3" server="wheelockslatin.com" local="3530667600" remote="3530667600" Dst="-1" /><file name="scriptor.mp3" server="wheelockslatin.com" local="3530667600" remote="3530667600" Dst="-1" /><file name="soror.mp3" server="wheelockslatin.com" local="3530667600" remote="3530667600" Dst="-1" /><file name="tamen.mp3" server="wheelockslatin.com" local="3530667600" remote="3530667600" Dst="-1" /><file name="traho.mp3" server="wheelockslatin.com" local="3530667600" remote="3530667600" Dst="-1" /><file name="victoria.mp3" server="wheelockslatin.com" local="3530667600" remote="3530667600" Dst="-1" /><file name="vinco.mp3" server="wheelockslatin.com" local="3530667600" remote="3530667600" Dst="-1" /></dwsync>