<?xml version="1.0" encoding="utf-8" ?><dwsync><file name="alo.mp3" server="wheelockslatin.com" local="3530667600" remote="3530667600" Dst="-1" /><file name="ante.mp3" server="wheelockslatin.com" local="3530667600" remote="3530667600" Dst="-1" /><file name="diligo.mp3" server="wheelockslatin.com" local="3530667600" remote="3530667600" Dst="-1" /><file name="divitiae.mp3" server="wheelockslatin.com" local="3530667600" remote="3530667600" Dst="-1" /><file name="doctus.mp3" server="wheelockslatin.com" local="3530667600" remote="3530667600" Dst="-1" /><file name="factum.mp3" server="wheelockslatin.com" local="3530667600" remote="3530667600" Dst="-1" /><file name="fortunatus.mp3" server="wheelockslatin.com" local="3530667600" remote="3530667600" Dst="-1" /><file name="ipse.mp3" server="wheelockslatin.com" local="3530667600" remote="3530667600" Dst="-1" /><file name="iungo.mp3" server="wheelockslatin.com" local="3530667600" remote="3530667600" Dst="-1" /><file name="nam.mp3" server="wheelockslatin.com" local="3530667600" remote="3530667600" Dst="-1" /><file name="olim.mp3" server="wheelockslatin.com" local="3530667600" remote="3530667600" Dst="-1" /><file name="per.mp3" server="wheelockslatin.com" local="3530667600" remote="3530667600" Dst="-1" /><file name="quisque.mp3" server="wheelockslatin.com" local="3530667600" remote="3530667600" Dst="-1" /><file name="signum.mp3" server="wheelockslatin.com" local="3530667600" remote="3530667600" Dst="-1" /><file name="sto.mp3" server="wheelockslatin.com" local="3530667600" remote="3530667600" Dst="-1" /><file name="sui.mp3" server="wheelockslatin.com" local="3530667600" remote="3530667600" Dst="-1" /><file name="suus.mp3" server="wheelockslatin.com" local="3530667600" remote="3530667600" Dst="-1" /></dwsync>